setup.py
hm_distributions/Binomialdistribution.py
hm_distributions/Gaussiandistribution.py
hm_distributions/Generaldistribution.py
hm_distributions/__init__.py
hm_distributions.egg-info/PKG-INFO
hm_distributions.egg-info/SOURCES.txt
hm_distributions.egg-info/dependency_links.txt
hm_distributions.egg-info/not-zip-safe
hm_distributions.egg-info/top_level.txt