Metadata-Version: 1.0
Name: hm-distributions
Version: 0.1
Summary: Gaussian and binomial hm_distributions
Home-page: UNKNOWN
Author: Olugbenga Abdulai
Author-email: abdulaigbenga96@gmail.com
License: UNKNOWN
Platform: UNKNOWN
